LICENSE
MANIFEST.in
README.md
requirements.txt
setup.cfg
setup.py
geococu/__init__.py
geococu/geococu.py
geococu.egg-info/PKG-INFO
geococu.egg-info/SOURCES.txt
geococu.egg-info/dependency_links.txt
geococu.egg-info/not-zip-safe
geococu.egg-info/top_level.txt