Metadata-Version: 2.1
Name: geococu
Version: 0.0.1
Summary: A python package for interactive mapping.
Home-page: https://github.com/Vaibhav170216/geococu
Author: Vaibhav Nagar
Author-email: vaib3hab@gmail.com
License: MIT license
Keywords: geococu
Platform: UNKNOWN
Classifier: Development Status :: 2 - Pre-Alpha
Classifier: Intended Audience :: Developers
Classifier: License :: OSI Approved :: MIT License
Classifier: Natural Language :: English
Classifier: Programming Language :: Python :: 3
Classifier: Programming Language :: Python :: 3.5
Classifier: Programming Language :: Python :: 3.6
Classifier: Programming Language :: Python :: 3.7
Classifier: Programming Language :: Python :: 3.8
Requires-Python: >=3.5
